subproj/__init__.py
subproj/__main__.py
subproj/logging.py
subproj/setup/__init__.py
subproj/setup/update.py
subproj/widget/__init__.py
subproj/widget/tk_base.py
subproj/widget/tk_commit.py
subproj/widget/tk_subproj.py
subproj/widget/actions/__init__.py
subproj/widget/actions/package_install.py
subproj/widget/startup/__init__.py
subproj/widget/startup/app_checks.py
subproj/widget/widgets/__init__.py
subproj/widget/widgets/button_quit.py
subproj/widget/widgets/label.py
subproj/widget/widgets/local_subproj_tree.py
subproj/widget/widgets/log.py
subproj/widget/widgets/remote_package_tree.py
subproj/widget/widgets/select_proj.py
subproj/widget/widgets/select_remote.py
subproj/widget/widgets/select_subproj.py
subproj/widget/widgets/startup_state.py
subproj/widget/widgets/worker_progress.py
subproj-0.0.1a2.dist-info/LICENSE.rst
subproj-0.0.1a2.dist-info/METADATA
subproj-0.0.1a2.dist-info/WHEEL
subproj-0.0.1a2.dist-info/entry_points.txt
subproj-0.0.1a2.dist-info/top_level.txt
subproj-0.0.1a2.dist-info/RECORD
