Metadata-Version: 2.1
Name: subproj
Version: 0.0.1a2
Summary: Handle PVSS subprojects
Home-page: https://gitlab.com/fholmer/subproj
Author: Frode Holmer
Author-email: fholmer+subproj@gmail.com
License: BSD-3-Clause
Project-URL: Documentation, https://fholmer.gitlab.io/subproj
Project-URL: Source Code, https://gitlab.com/fholmer/subproj
Keywords: subproj,subprojects,deploy,install,on-prem,pvss
Classifier: Development Status :: 4 - Beta
Classifier: Intended Audience :: Developers
Classifier: License :: OSI Approved :: BSD License
Classifier: Operating System :: OS Independent
Classifier: Programming Language :: Python :: 3
Classifier: Programming Language :: Python :: 3.9
Classifier: Programming Language :: Python :: 3.10
Classifier: Programming Language :: Python :: 3.11
License-File: LICENSE.rst
Requires-Dist: adop
Requires-Dist: keyring
